setup.py
hieropt/OrderedDict.py
hieropt/__init__.py
hieropt.egg-info/PKG-INFO
hieropt.egg-info/SOURCES.txt
hieropt.egg-info/dependency_links.txt
hieropt.egg-info/top_level.txt
hieropt/test/__init__.py
hieropt/test/test_hieropt.py