Metadata-Version: 1.0
Name: hieropt
Version: 0.3
Summary: Simple, hierarchical configuration; able to read configuration
Home-page: UNKNOWN
Author: Jeremy Fincher
Author-email: jemfinch@finchers.us
License: BSD
Keywords: hierarchical configuration options
Platform: UNKNOWN
